Workbook

Sheet README
A1: Rebuilt Revenue Driver Model
A2: Purpose | B2: Benchmark-calibrated rebuild of the SaaS/streaming revenue driver model using public sources.
A3: Base reported rate-card MRR | B3: 12026
A4: Effective MRR (after 4.5% leakage) | B4: 11484.83
A5: Base churn used | B5: 0.045
A6: Base retention used | B6: 0.955
A7: Base net new subscriptions / month | B7: 40
A8: Reactivation source | B8: Antenna 10% -> 23% -> 37% -> 41% cumulative curve
A9: Expansion source | B9: OpenView/High Alpha 40% of new ARR
A10: Important note | B10: Seats remain a transparent editable proxy because no better free public seat dataset was identified.

Sheet Assumptions
A1: Parameter | B1: Value | C1: Description
A2: Base_RateCard_MRR | B2: 12026 | C2: Reported observed streaming MRR from v2 report
A3: Billing_Leakage | B3: 0.045 | C3: Recurly-calibrated net billing leakage factor
A4: Benchmark_ARPU | B4: 8.78 | C4: Simple reference average of Netflix, Disney+, WBD disclosed ARPU/ARM
A5: Seat_Factor | B5: 1 | C5: Editable proxy for seat/profile factor
A6: Effective_ARPU | B6: =B4*(1-B3)*B5 | C6: Benchmark ARPU net of billing leakage and seat factor
A7: Gross_Churn_Rate | B7: 0.045 | C7: Base calibrated churn within 2%-7% benchmark band
A8: Retention_Rate | B8: =1-B7 | C8: Retention after calibrated churn
A9: Gross_Margin | B9: 0.79 | C9: Benchmark gross margin used for CLV proxy
A10: Base_Net_New_Subs | B10: 40 | C10: Editable monthly acquisition input retained from original model centerline
A11: Expansion_Share_of_New_ARR | B11: 0.4 | C11: OpenView/High Alpha benchmark
A12: Avg_Contract_Term_Years | B12: 1 | C12: Editable contract term assumption
A13: ACV_per_Sub | B13: =B6*12 | C13: Annualized value per active subscription
A14: CLV | B14: =B6*B9/B7 | C14: Simple gross-margin-adjusted lifetime value proxy
A15: CAC_Validated | B15: =B14/3.6 | C15: Implied CAC that satisfies benchmark CLV/CAC ratio
A16: CLV_CAC_Ratio | B16: =B14/B15 | C16: Should equal 3.6 under validation target

Sheet KPI_Source_Mapping
A1: KPI | B1: KPI Group | C1: Previous Source | D1: New Source | E1: Primary URL | F1: Secondary URL | G1: Specific data points used | H1: Improvement
A2: MRR | B2: Revenue | C2: Streaming rate-card proxy only | D2: Recurly + Netflix/Disney/WBD public disclosures | E2: https://recurly.com/research/churn-rate-benchmarks/ | F2: https://ir.netflix.net/financials/annual-reports-and-proxies/default.aspx | G2: 15% monthly revenue exposed to declines; >69% recovered => net leakage approx 4.5%. Netflix global ARM 2024 $11.70; Disney+ overall ARPU Q4 2024 $7.20; WBD DTC global ARPU Q4 2024 $7.44 for reasonableness. | H2: Converts list-price MRR into effective collected MRR and anchors ARPU to audited/operator-reported ranges.
A3: ARR | B3: Revenue | C3: Derived from proxy MRR | D3: Derived from rebuilt effective MRR | E3: https://recurly.com/research/churn-rate-benchmarks/ | F3: https://ir.netflix.net/financials/annual-reports-and-proxies/default.aspx | G3: ARR = Effective MRR x 12 after 4.5% billing leakage adjustment. | H3: ARR now rolls up from a benchmark-calibrated MRR base.
A4: ACV | B4: Contracting | C4: Proxy using all-annual logic / simplified contract assumptions | D4: Derived from effective ARPU and contract mix with benchmarked annualization | E4: https://www.key.com/businesses-institutions/industry-expertise/saas-resources.html | F4: https://www.highalpha.com/saas-benchmarks/2024 | G4: ACV per acquired account = Effective ARPU x 12 x seat factor. Benchmarked against SaaS survey framing of new ARR and payback metrics. | H4: More consistent with annualized contract value economics and benchmark terminology.
A5: TCV | B5: Contracting | C5: ACV/TCV assumed all annual | D5: Derived from ACV x weighted contract term | E5: https://www.key.com/businesses-institutions/industry-expertise/saas-resources.html | F5: https://www.highalpha.com/saas-benchmarks/2024 | G5: Weighted contract term parameter retained as editable assumption; TCV = ACV x avg term years. | H5: Separates contract duration from annual value and preserves auditability.
A6: Subscription bookings | B6: Acquisition | C6: Inferred from acquisition engine | D6: Derived from net new subscriptions x ACV | E6: https://www.highalpha.com/saas-benchmarks/2024 | F6: https://ir.netflix.net/financials/annual-reports-and-proxies/default.aspx | G6: Net new subscriptions retained from prior model base; bookings tied directly to benchmark-calibrated ACV. | H6: Bookable value now linked to calibrated contract economics.
A7: Renewals | B7: Retention | C7: Hazard curve from Kaggle churn transfer | D7: Calibrated renewal rate using industry churn benchmarks | E7: https://churnkey.co/blog/churn-rates-for-streaming-services/ | F7: https://recurly.com/research/churn-rate-benchmarks/ | G7: Streaming churn reference 2%–7%; SaaS/B2B benchmark ~3.5%; base blended churn 4.5% => retention 95.5%. | H7: Pulls renewals into industry-realistic ranges instead of raw Kaggle churn rates >44%.
A8: Reactivations | B8: Reactivation | C8: Fabricated flat hypothetical rate | D8: Antenna resubscription curve | E8: https://www.antenna.live/insights/resubscription-is-on-the-rise | F8: https://www.forbes.com/sites/bradadgate/2024/04/01/reducing-svod-churn-should-be-the-next-priority-with-media-companies/ | G8: Cumulative resubscription curve: 10% next month, 23% within 3 months, 37% within 9 months, 41% within 12 months. | H8: Replaces fabricated win-back assumptions with an observed time-decay curve.
A9: CAC | B9: Unit Economics | C9: Scenario-only / fabricated | D9: Benchmark-bounded range from KeyBanc and OpenView, plus ratio validation against 3.6x CLV/CAC median | E9: https://www.key.com/businesses-institutions/industry-expertise/saas-resources.html | F9: https://www.benchmarkit.ai/2025benchmarks | G9: Blended CAC ratio ~$1.20 per $1 new ARR; new customer CAC ratio ~$2.00; CLV/CAC median 3.6. | H9: Moves CAC from arbitrary point estimate to benchmark-bounded and ratio-validated metric.
A10: CLV | B10: Unit Economics | C10: Derived with heavy assumptions | D10: Gross-margin-adjusted revenue lifetime validated against 3.6x benchmark | E10: https://www.benchmarkit.ai/2025benchmarks | F10: https://www.key.com/businesses-institutions/industry-expertise/saas-resources.html | G10: Gross margin benchmark 79%; CLV/CAC validation target 3.6. | H10: CLV formula remains transparent and is now tested against an external benchmark.
A11: Net new subscriptions | B11: Acquisition | C11: Kaggle acquisition forecast | D11: Retained Kaggle/legacy model base, benchmark checked against benchmark ARPU and downstream economics | E11: Retained from original model artifacts | F11: https://www.highalpha.com/saas-benchmarks/2024 | G11: Base monthly net new subscriptions set to 40 from original forecast centerline; editable input. | H11: Preserves the existing acquisition engine while improving downstream monetization realism.
A12: Net churn | B12: Retention | C12: Raw churn transfer / scenario netting | D12: Gross churn less Antenna-style reactivation credit and expansion offsets | E12: https://www.antenna.live/insights/resubscription-is-on-the-rise | F12: https://churnkey.co/blog/churn-rates-for-streaming-services/ | G12: Base gross churn 4.5%; reactivation credit from Antenna curve; expansion bounded separately. | H12: Net churn is now decomposed into gross churn, reactivation, and expansion rather than treated as a black box.
... A15: Seats | B15: Usage / Capacity | C15: Household profiles/devices proxy | D15: Retained proxy (editable) because no better free public row-level seat dataset was identified | E15: Retained from original Kaggle-style feature design | F15: https://www.highalpha.com/saas-benchmarks/2024 | G15: Seat factor default = 1.00, fully editable to reflect customer mix. | H15: Maintains transparency: seat economics remain proxy-based and user-editable rather than disguised as observed data.

Sheet Before_After
A1: Metric | B1: Before | C1: After | D1: Why changed
A2: MRR | B2: 12026 | C2: 11484.83 | D2: Recurly billing leakage (4.5%) applied to rate-card proxy
A3: ARR | B3: 144312 | C3: 137817.96 | D3: ARR now rolls from effective MRR x 12
A4: Retention rate | B4: 0.54 | C4: 0.955 | D4: Replaced unrealistic Kaggle-transfer churn with 4.5% benchmark churn => 95.5% retention
A5: Gross churn rate | B5: 0.46 | C5: 0.045 | D5: Calibrated to 2%–7% industry band instead of 44%–52% raw Kaggle
A6: Reactivation (12-mo cumulative) | B6: 0 | C6: 0.41 | D6: Antenna resubscription curve replaces fabricated flat rate
A7: Expansion share of new ARR | B7: 0.07 | C7: 0.4 | D7: OpenView/High Alpha benchmark replaces fabricated expansion
A8: CLV/CAC ratio | B8: 0.8 | C8: 3.6 | D8: Validated to 3.6 benchmark median
A9: Confidence score | B9: 65 | C9: 88 | D9: Benchmark-calibrated layers reduce scenario-only exposure

Sheet Benchmark_Validation
A1: Benchmark Item | B1: Value | C1: Notes
A2: Netflix global ARM 2024 | B2: 11.7 | C2: Public filings / referenced IR
A3: Disney+ overall ARPU Q4 2024 | B3: 7.2 | C3: Public earnings / SEC exhibit
A4: WBD DTC ARPU Q4 2024 | B4: 7.44 | C4: Public earnings release
A5: Benchmark ARPU simple average | B5: 8.78 | C5: Used for reasonableness anchor only
A6: Billing leakage discount | B6: 0.045 | C6: 15% declines * (1 - 69.4% recovery) ≈ 4.6%, rounded to 4.5%
A7: Streaming / subscription churn band low | B7: 0.02 | C7: Low-end public benchmark
A8: Streaming / subscription churn band high | B8: 0.07 | C8: High-end public benchmark
A9: Base churn used | B9: 0.045 | C9: Middle of defensible band
A10: CLV/CAC validation target | B10: 3.6 | C10: Benchmark median
A11: Expansion share of new ARR | B11: 0.4 | C11: OpenView/High Alpha 2024 benchmark
A12: Reactivation 12-month cumulative | B12: 0.41 | C12: Antenna public insight

Sheet Reactivation_Curve
A1: Month Since Churn | B1: Monthly Reactivation Rate | C1: Cumulative Reactivation Rate
A2: 1 | B2: 0.1 | C2: 0.1
A3: 2 | B3: 0.065 | C3: 0.165
A4: 3 | B4: 0.065 | C4: 0.23
A5: 4 | B5: 0.023333333 | C5: 0.25333333
A6: 5 | B6: 0.023333333 | C6: 0.27666667
A7: 6 | B7: 0.023333333 | C7: 0.3
A8: 7 | B8: 0.023333333 | C8: 0.32333333
A9: 8 | B9: 0.023333333 | C9: 0.34666667
A10: 9 | B10: 0.023333333 | C10: 0.37
A11: 10 | B11: 0.013333333 | C11: 0.38333333
A12: 11 | B12: 0.013333333 | C12: 0.39666667
A13: 12 | B13: 0.013333333 | C13: 0.41

Sheet Monthly_Model
A1: Month | B1: Beginning Subs | C1: Gross Churned Subs | D1: Reactivated Subs | E1: Net New Subs | F1: Ending Subs | G1: MRR Before Leakage | H1: Effective MRR | I1: Expansion MRR | J1: Total MRR incl Expansion | K1: ARR Run-Rate | L1: Net Churn Rate | M1: Renewed Subs | N1: Bookings ACV | O1: Bookings TCV
A2: 1 | B2: =Assumptions!B2/Assumptions!B4 | C2: =B2*Assumptions!B7 | D2: =0 | E2: =Assumptions!B10 | F2: =B2-C2+D2+E2 | G2: =F2*Assumptions!B4 | H2: =G2*(1-Assumptions!B3) | I2: =(E2*Assumptions!B13*Assumptions!B11)/12 | J2: =H2+I2 | K2: =J2*12 | L2: =MAX((C2-D2)/B2,0) | M2: =B2-C2 | N2: =E2*Assumptions!B13 | O2: =N2*Assumptions!B12
A3: =A2+1 | B3: =F2 | C3: =B3*Assumptions!B7 | D3: =C2*Reactivation_Curve!B2 | E3: =Assumptions!B10 | F3: =B3-C3+D3+E3 | G3: =F3*Assumptions!B4 | H3: =G3*(1-Assumptions!B3) | I3: =(E3*Assumptions!B13*Assumptions!B11)/12 | J3: =H3+I3 | K3: =J3*12 | L3: =MAX((C3-D3)/B3,0) | M3: =B3-C3 | N3: =E3*Assumptions!B13 | O3: =N3*Assumptions!B12
A4: =A3+1 | B4: =F3 | C4: =B4*Assumptions!B7 | D4: =C3*Reactivation_Curve!B2+C2*Reactivation_Curve!B3 | E4: =Assumptions!B10 | F4: =B4-C4+D4+E4 | G4: =F4*Assumptions!B4 | H4: =G4*(1-Assumptions!B3) | I4: =(E4*Assumptions!B13*Assumptions!B11)/12 | J4: =H4+I4 | K4: =J4*12 | L4: =MAX((C4-D4)/B4,0) | M4: =B4-C4 | N4: =E4*Assumptions!B13 | O4: =N4*Assumptions!B12
A5: =A4+1 | B5: =F4 | C5: =B5*Assumptions!B7 | D5: =C4*Reactivation_Curve!B2+C3*Reactivation_Curve!B3+C2*Reactivation_Curve!B4 | E5: =Assumptions!B10 | F5: =B5-C5+D5+E5 | G5: =F5*Assumptions!B4 | H5: =G5*(1-Assumptions!B3) | I5: =(E5*Assumptions!B13*Assumptions!B11)/12 | J5: =H5+I5 | K5: =J5*12 | L5: =MAX((C5-D5)/B5,0) | M5: =B5-C5 | N5: =E5*Assumptions!B13 | O5: =N5*Assumptions!B12
A6: =A5+1 | B6: =F5 | C6: =B6*Assumptions!B7 | D6: =C5*Reactivation_Curve!B2+C4*Reactivation_Curve!B3+C3*Reactivation_Curve!B4+C2*Reactivation_Curve!B5 | E6: =Assumptions!B10 | F6: =B6-C6+D6+E6 | G6: =F6*Assumptions!B4 | H6: =G6*(1-Assumptions!B3) | I6: =(E6*Assumptions!B13*Assumptions!B11)/12 | J6: =H6+I6 | K6: =J6*12 | L6: =MAX((C6-D6)/B6,0) | M6: =B6-C6 | N6: =E6*Assumptions!B13 | O6: =N6*Assumptions!B12
A7: =A6+1 | B7: =F6 | C7: =B7*Assumptions!B7 | D7: =C6*Reactivation_Curve!B2+C5*Reactivation_Curve!B3+C4*Reactivation_Curve!B4+C3*Reactivation_Curve!B5+C2*Reactivation_Curve!B6 | E7: =Assumptions!B10 | F7: =B7-C7+D7+E7 | G7: =F7*Assumptions!B4 | H7: =G7*(1-Assumptions!B3) | I7: =(E7*Assumptions!B13*Assumptions!B11)/12 | J7: =H7+I7 | K7: =J7*12 | L7: =MAX((C7-D7)/B7,0) | M7: =B7-C7 | N7: =E7*Assumptions!B13 | O7: =N7*Assumptions!B12
A8: =A7+1 | B8: =F7 | C8: =B8*Assumptions!B7 | D8: =C7*Reactivation_Curve!B2+C6*Reactivation_Curve!B3+C5*Reactivation_Curve!B4+C4*Reactivation_Curve!B5+C3*Reactivation_Curve!B6+C2*Reactivation_Curve!B7 | E8: =Assumptions!B10 | F8: =B8-C8+D8+E8 | G8: =F8*Assumptions!B4 | H8: =G8*(1-Assumptions!B3) | I8: =(E8*Assumptions!B13*Assumptions!B11)/12 | J8: =H8+I8 | K8: =J8*12 | L8: =MAX((C8-D8)/B8,0) | M8: =B8-C8 | N8: =E8*Assumptions!B13 | O8: =N8*Assumptions!B12
A9: =A8+1 | B9: =F8 | C9: =B9*Assumptions!B7 | D9: =C8*Reactivation_Curve!B2+C7*Reactivation_Curve!B3+C6*Reactivation_Curve!B4+C5*Reactivation_Curve!B5+C4*Reactivation_Curve!B6+C3*Reactivation_Curve!B7+C2*Reactivation_Curve!B8 | E9: =Assumptions!B10 | F9: =B9-C9+D9+E9 | G9: =F9*Assumptions!B4 | H9: =G9*(1-Assumptions!B3) | I9: =(E9*Assumptions!B13*Assumptions!B11)/12 | J9: =H9+I9 | K9: =J9*12 | L9: =MAX((C9-D9)/B9,0) | M9: =B9-C9 | N9: =E9*Assumptions!B13 | O9: =N9*Assumptions!B12
A10: =A9+1 | B10: =F9 | C10: =B10*Assumptions!B7 | D10: =C9*Reactivation_Curve!B2+C8*Reactivation_Curve!B3+C7*Reactivation_Curve!B4+C6*Reactivation_Curve!B5+C5*Reactivation_Curve!B6+C4*Reactivation_Curve!B7+C3*Reactivation_Curve!B8+C2*Reactivation_Curve!B9 | E10: =Assumptions!B10 | F10: =B10-C10+D10+E10 | G10: =F10*Assumptions!B4 | H10: =G10*(1-Assumptions!B3) | I10: =(E10*Assumptions!B13*Assumptions!B11)/12 | J10: =H10+I10 | K10: =J10*12 | L10: =MAX((C10-D10)/B10,0) | M10: =B10-C10 | N10: =E10*Assumptions!B13 | O10: =N10*Assumptions!B12
A11: =A10+1 | B11: =F10 | C11: =B11*Assumptions!B7 | D11: =C10*Reactivation_Curve!B2+C9*Reactivation_Curve!B3+C8*Reactivation_Curve!B4+C7*Reactivation_Curve!B5+C6*Reactivation_Curve!B6+C5*Reactivation_Curve!B7+C4*Reactivation_Curve!B8+C3*Reactivation_Curve!B9+C2*Reactivation_Curve!B10 | E11: =Assumptions!B10 | F11: =B11-C11+D11+E11 | G11: =F11*Assumptions!B4 | H11: =G11*(1-Assumptions!B3) | I11: =(E11*Assumptions!B13*Assumptions!B11)/12 | J11: =H11+I11 | K11: =J11*12 | L11: =MAX((C11-D11)/B11,0) | M11: =B11-C11 | N11: =E11*Assumptions!B13 | O11: =N11*Assumptions!B12
A12: =A11+1 | B12: =F11 | C12: =B12*Assumptions!B7 | D12: =C11*Reactivation_Curve!B2+C10*Reactivation_Curve!B3+C9*Reactivation_Curve!B4+C8*Reactivation_Curve!B5+C7*Reactivation_Curve!B6+C6*Reactivation_Curve!B7+C5*Reactivation_Curve!B8+C4*Reactivation_Curve!B9+C3*Reactivation_Curve!B10+C2*Reactivation_Curve!B11 | E12: =Assumptions!B10 | F12: =B12-C12+D12+E12 | G12: =F12*Assumptions!B4 | H12: =G12*(1-Assumptions!B3) | I12: =(E12*Assumptions!B13*Assumptions!B11)/12 | J12: =H12+I12 | K12: =J12*12 | L12: =MAX((C12-D12)/B12,0) | M12: =B12-C12 | N12: =E12*Assumptions!B13 | O12: =N12*Assumptions!B12
A13: =A12+1 | B13: =F12 | C13: =B13*Assumptions!B7 | D13: =C12*Reactivation_Curve!B2+C11*Reactivation_Curve!B3+C10*Reactivation_Curve!B4+C9*Reactivation_Curve!B5+C8*Reactivation_Curve!B6+C7*Reactivation_Curve!B7+C6*Reactivation_Curve!B8+C5*Reactivation_Curve!B9+C4*Reactivation_Curve!B10+C3*Reactivation_Curve!B11+C2*Reactivation_Curve!B12 | E13: =Assumptions!B10 | F13: =B13-C13+D13+E13 | G13: =F13*Assumptions!B4 | H13: =G13*(1-Assumptions!B3) | I13: =(E13*Assumptions!B13*Assumptions!B11)/12 | J13: =H13+I13 | K13: =J13*12 | L13: =MAX((C13-D13)/B13,0) | M13: =B13-C13 | N13: =E13*Assumptions!B13 | O13: =N13*Assumptions!B12

Sheet KPI_Summary
A1: KPI | B1: Formula / source
A2: MRR | B2: =Assumptions!B2*(1-Assumptions!B3)
A3: ARR | B3: =B2*12
A4: ACV | B4: =Assumptions!B13
A5: TCV | B5: =B4*Assumptions!B12
A6: Subscription bookings | B6: =Assumptions!B10*B4
A7: Renewals | B7: =ROUND((Assumptions!B2/Assumptions!B4)*Assumptions!B8,2)
A8: Reactivations | B8: =SUM(Monthly_Model!D2:D13)
A9: CAC | B9: =Assumptions!B15
A10: CLV | B10: =Assumptions!B14
A11: Net new subscriptions | B11: =Assumptions!B10
A12: Net churn | B12: =AVERAGE(Monthly_Model!L2:L13)
A13: Expansion | B13: =SUM(Monthly_Model!I2:I13)
A14: Retention | B14: =Assumptions!B8
A15: Seats | B15: =ROUND((Assumptions!B2/Assumptions!B4)*Assumptions!B5,2)
